README.md
setup.py
mastocount/__init__.py
mastocount/cfgparse.py
mastocount/cliparse.py
mastocount/elasticsearch.py
mastocount/followers.py
mastocount/main.py
mastocount/prettyprint.py
mastocount/total.py
mastocount.egg-info/PKG-INFO
mastocount.egg-info/SOURCES.txt
mastocount.egg-info/dependency_links.txt
mastocount.egg-info/requires.txt
mastocount.egg-info/top_level.txt
mastocount/cfgparsers/__init__.py
mastocount/cfgparsers/elasticsearch.py
scripts/mastocount
scripts/register_mastocount_app