Metadata-Version: 1.1
Name: mastocount
Version: 0.3
Summary: Mastocount retrieves the number of followers of these accounts and print detailed numbers and the total number
Home-page: https://gitlab.com/chaica/mastocount
Author: Carl Chenet
Author-email: chaica@ohmytux.com
License: GNU GPL v3
Download-URL: https://gitlab.com/chaica/mastocount
Platform: UNKNOWN
Classifier: Intended Audience :: End Users/Desktop
Classifier: Environment :: Console
Classifier: License :: OSI Approved :: GNU General Public License (GPL)
Classifier: Operating System :: POSIX :: Linux
Classifier: Programming Language :: Python :: 3.4
Classifier: Programming Language :: Python :: 3.5
Classifier: Programming Language :: Python :: 3.6
